pandoc_inplace_include/main.py
pandoc_inplace_include-0.0.2.dist-info/METADATA
pandoc_inplace_include-0.0.2.dist-info/WHEEL
pandoc_inplace_include-0.0.2.dist-info/entry_points.txt
pandoc_inplace_include-0.0.2.dist-info/top_level.txt
pandoc_inplace_include-0.0.2.dist-info/RECORD
