Metadata-Version: 2.1
Name: pandoc-inplace-include
Version: 0.0.2
Summary: Pandoc filter to allow file inplace includes
Home-page: https://github.com/zhijie-yang/pandoc-inplace-include
Author: zhijie-yang
Author-email: zhijie.yang@canonical.com
License: MIT
Classifier: Environment :: Console
Classifier: Intended Audience :: End Users/Desktop
Classifier: Programming Language :: Python
Classifier: License :: OSI Approved :: MIT License
Requires-Dist: pandocfilters
